__init__.py
harrevelt_tools/__init__.py
harrevelt_tools/example.py
harrevelt_tools/helper/__init__.py
harrevelt_tools/helper/data_transform.py
harrevelt_tools/helper/plot.py
harrevelt_tools-0.0.2.dist-info/LICENSE
harrevelt_tools-0.0.2.dist-info/METADATA
harrevelt_tools-0.0.2.dist-info/WHEEL
harrevelt_tools-0.0.2.dist-info/top_level.txt
harrevelt_tools-0.0.2.dist-info/RECORD
